tabnews/__init__.py
tabnews/config.py
tabnews/exceptions.py
tabnews/utils.py
tabnews/mixins/__init__.py
tabnews/mixins/account.py
tabnews/mixins/auth.py
tabnews/mixins/comments.py
tabnews/mixins/posts.py
tabnews/mixins/private.py
tabnews/mixins/tabcoins.py
tabnews-1.2.0.dist-info/LICENSE
tabnews-1.2.0.dist-info/METADATA
tabnews-1.2.0.dist-info/WHEEL
tabnews-1.2.0.dist-info/top_level.txt
tabnews-1.2.0.dist-info/RECORD
