Metadata-Version: 2.1
Name: tabnews
Version: 1.2.0
Summary: Python library for communication via API to the website: "TabNews.com.br"
Home-page: https://github.com/Gustavosta/Tabnews.py
Author: Gustavo Santana
Author-email: sowlfie@gmail.com
License: MIT
Keywords: api,tabnews,tabcoins
Classifier: Programming Language :: Python :: 3
Classifier: License :: OSI Approved :: MIT License
Classifier: Operating System :: OS Independent
Requires-Python: >=3.7
License-File: LICENSE
Requires-Dist: cleverdict
Requires-Dist: requests
